accessor/configLoader.py
accessor/spotifyAccessor.py
dependency/spotifyClient.py
logic/actionValidator.py
logic/playlistLogic.py
logic/mapper/spotifyMapper.py
models/actions.py
service/cli.py
service/mainHandler.py
service/onDemandHandler.py
service/schedulerHandler.py
service/helper/actionHelper.py
spotify_actions-0.1.3.dist-info/licenses/LICENSE
util/env.py
util/logger.py
spotify_actions-0.1.3.dist-info/METADATA
spotify_actions-0.1.3.dist-info/WHEEL
spotify_actions-0.1.3.dist-info/entry_points.txt
spotify_actions-0.1.3.dist-info/top_level.txt
spotify_actions-0.1.3.dist-info/RECORD
