Metadata-Version: 2.4
Name: spotify-actions
Version: 0.1.3
Summary: Schedule Actions on Spotify
Author: Joshua Prier
License: MIT License
Project-URL: Homepage, https://github.com/JPrier/SpotifyActionScheduler
Project-URL: Repository, https://github.com/JPrier/SpotifyActionScheduler
Classifier: Programming Language :: Python :: 3
Classifier: Programming Language :: Python :: 3.13
Classifier: License :: OSI Approved :: MIT License
Classifier: Operating System :: OS Independent
Requires-Python: >=3.13
License-File: LICENSE
Requires-Dist: python-dotenv>=1.0.0
Requires-Dist: spotipy>=2.0.0
Requires-Dist: schedule>=1.0.0
Requires-Dist: click>=8.0
Provides-Extra: dev
Requires-Dist: coverage>=7.8.0; extra == "dev"
Requires-Dist: just>=0.8.162; extra == "dev"
Requires-Dist: pytest>=8.3.5; extra == "dev"
Requires-Dist: pytest-cov>=6.1.1; extra == "dev"
Requires-Dist: ruff>=0.11.8; extra == "dev"
Requires-Dist: typing-extensions>=4.13.2; extra == "dev"
Dynamic: license-file
